setup.py
debris/__init__.py
debris/asset.py
debris/cache.py
debris/helpers.py
debris.egg-info/PKG-INFO
debris.egg-info/SOURCES.txt
debris.egg-info/dependency_links.txt
debris.egg-info/top_level.txt
debris.egg-info/zip-safe