Metadata-Version: 1.1
Name: debris
Version: 0.0.1
Summary: Recycle your objects
Home-page: http://github.com/stevepeak/debris
Author: @stevepeak
Author-email: steve@stevepeak.net
License: http://www.apache.org/licenses/LICENSE-2.0
Keywords: cache tornado
Platform: UNKNOWN
Classifier: Development Status :: 1 - Planning
Classifier: License :: OSI Approved :: Apache Software License
Classifier: Programming Language :: Python
Classifier: Programming Language :: Python :: 2.6
Classifier: Programming Language :: Python :: 2.7
Classifier: Programming Language :: Python :: 3.2
Classifier: Programming Language :: Python :: 3.3
Classifier: Programming Language :: Python :: Implementation :: PyPy
